pingsweep.py
pingsweep-0.1.2.data/scripts/pingsweep
pingsweep-0.1.2.dist-info/DESCRIPTION.rst
pingsweep-0.1.2.dist-info/METADATA
pingsweep-0.1.2.dist-info/RECORD
pingsweep-0.1.2.dist-info/WHEEL
pingsweep-0.1.2.dist-info/metadata.json
pingsweep-0.1.2.dist-info/top_level.txt
