Metadata-Version: 2.0
Name: pingsweep
Version: 0.1.2
Summary: IPv4 Ping Sweep Scan Utility
Home-page: https://github.com/sirpsycho/pingsweep
Author: sirpsycho
Author-email: UNKNOWN
License: MIT
Keywords: pingsweep,scan,icmp
Platform: UNKNOWN
Classifier: Development Status :: 3 - Alpha
Classifier: License :: OSI Approved :: MIT License
Classifier: Programming Language :: Python
Classifier: Programming Language :: Python :: 2
Classifier: Programming Language :: Python :: 3
Requires-Dist: netaddr (>=0.7.18)
